sublogs/__init__.py
sublogs/mongoHandler.py
sublogs-0.0.1.dist-info/METADATA
sublogs-0.0.1.dist-info/WHEEL
sublogs-0.0.1.dist-info/top_level.txt
sublogs-0.0.1.dist-info/RECORD
